[
  {
    "lines": [
      {
        "message": "C:\\Users\\Alexander> ls",
        "type": "command"
      },
      {
        "message": "08.11.2015  14:17  DIR            .",
        "type": "default"
      },
      {
        "message": "05.08.2015  23:27  DIR            ..",
        "type": "default"
      },
      {
        "message": "31.10.2015  15:28  DIR            .atom",
        "type": "default"
      },
      {
        "message": "27.06.2015  20:27  DIR            .config",
        "type": "default"
      },
      {
        "message": "08.05.2014  22:59  DIR            .eclipse",
        "type": "default"
      },
      {
        "message": "08.11.2015  20:03  DIR            .electron",
        "type": "default"
      },
      {
        "message": "08.11.2015  14:17           145 B .gitconfig",
        "type": "default"
      },
      {
        "message": "20.04.2014  13:32  DIR            .minion",
        "type": "default"
      },
      {
        "message": "23.06.2014  19:16  DIR            .ssh",
        "type": "default"
      },
      {
        "message": "07.06.2015  16:44  DIR            .thumbnails",
        "type": "default"
      },
      {
        "message": "26.04.2014  14:03  DIR            .VirtualBox",
        "type": "default"
      },
      {
        "message": "27.06.2015  21:48  DIR            .WebStorm10",
        "type": "default"
      },
      {
        "message": "04.06.2014  21:28  DIR            .WebStorm8",
        "type": "default"
      },
      {
        "message": "20.06.2015  15:08           135 B .yo-rc-global.json",
        "type": "default"
      },
      {
        "message": "06.08.2015  18:46  DIR            3D Objects",
        "type": "default"
      },
      {
        "message": "31.10.2015  15:24  DIR            Anwendungsdaten",
        "type": "default"
      },
      {
        "message": "05.08.2015  23:26  DIR            AppData",
        "type": "default"
      },
      {
        "message": "22.03.2014  12:31  DIR            Application Data",
        "type": "default"
      },
      {
        "message": "08.05.2014  22:58  DIR            Aptana Rubles",
        "type": "default"
      },
      {
        "message": "26.10.2015  20:19  DIR            Contacts",
        "type": "default"
      },
      {
        "message": "08.11.2015  22:50  DIR            Cookies",
        "type": "default"
      },
      {
        "message": "08.11.2015  23:00  DIR            Desktop",
        "type": "default"
      },
      {
        "message": "04.11.2015  08:34  DIR            Documents",
        "type": "default"
      },
      {
        "message": "08.11.2015  23:21  DIR            Downloads",
        "type": "default"
      },
      {
        "message": "10.07.2015  13:04  DIR            Druckumgebung",
        "type": "default"
      },
      {
        "message": "04.11.2015  08:34  DIR            Eigene Dateien",
        "type": "default"
      },
      {
        "message": "26.10.2015  20:19  DIR            Favorites",
        "type": "default"
      },
      {
        "message": "26.10.2015  20:19  DIR            Links",
        "type": "default"
      },
      {
        "message": "08.11.2015  13:02  DIR            Lokale Einstellungen",
        "type": "default"
      },
      {
        "message": "26.10.2015  20:19  DIR            Music",
        "type": "default"
      },
      {
        "message": "10.07.2015  13:04  DIR            Netzwerkumgebung",
        "type": "default"
      },
      {
        "message": "08.11.2015  03:31          3.7 MB NTUSER.DAT",
        "type": "default"
      },
      {
        "message": "05.08.2015  23:25        964.6 kB ntuser.dat.LOG1",
        "type": "default"
      },
      {
        "message": "05.08.2015  23:25        983.0 kB ntuser.dat.LOG2",
        "type": "default"
      },
      {
        "message": "17.10.2015  01:41         65.5 kB NTUSER.DAT{adb23442-271f-11e5-80dd-e41d2d719220}.TM.blf",
        "type": "default"
      },
      {
        "message": "17.10.2015  01:41        524.3 kB NTUSER.DAT{adb23442-271f-11e5-80dd-e41d2d719220}.TMContainer00000000000000000001.regtrans-ms",
        "type": "default"
      },
      {
        "message": "05.08.2015  23:25        524.3 kB NTUSER.DAT{adb23442-271f-11e5-80dd-e41d2d719220}.TMContainer00000000000000000002.regtrans-ms",
        "type": "default"
      },
      {
        "message": "06.08.2015  08:02            20 B ntuser.ini",
        "type": "default"
      },
      {
        "message": "06.08.2015  08:06  DIR            OneDrive",
        "type": "default"
      },
      {
        "message": "08.11.2015  23:16  DIR            Pictures",
        "type": "default"
      },
      {
        "message": "08.05.2014  22:42  DIR            projects",
        "type": "default"
      },
      {
        "message": "08.11.2015  23:21  DIR            Recent",
        "type": "default"
      },
      {
        "message": "26.10.2015  20:19  DIR            Saved Games",
        "type": "default"
      },
      {
        "message": "26.10.2015  20:19  DIR            Searches",
        "type": "default"
      },
      {
        "message": "16.10.2015  21:46  DIR            SendTo",
        "type": "default"
      },
      {
        "message": "07.08.2015  20:42  DIR            SkyDrive",
        "type": "default"
      },
      {
        "message": "31.03.2014  17:31  DIR            SkyDrive.old",
        "type": "default"
      },
      {
        "message": "26.10.2015  20:19  DIR            Startmenü",
        "type": "default"
      },
      {
        "message": "16.10.2015  21:47  DIR            Tracing",
        "type": "default"
      },
      {
        "message": "20.06.2015  00:20  DIR            typings",
        "type": "default"
      },
      {
        "message": "08.11.2015  13:06  DIR            Videos",
        "type": "default"
      },
      {
        "message": "26.04.2014  14:01  DIR            VirtualBox VMs",
        "type": "default"
      },
      {
        "message": "10.07.2015  13:04  DIR            Vorlagen",
        "type": "default"
      },
      {
        "message": "03.10.2015  09:09  DIR            WebstormProjects",
        "type": "default"
      },
      {
        "message": "C:\\Users\\Alexander> ls",
        "type": "command"
      },
      {
        "message": "08.11.2015  14:17  DIR            .",
        "type": "default"
      },
      {
        "message": "05.08.2015  23:27  DIR            ..",
        "type": "default"
      },
      {
        "message": "31.10.2015  15:28  DIR            .atom",
        "type": "default"
      },
      {
        "message": "27.06.2015  20:27  DIR            .config",
        "type": "default"
      },
      {
        "message": "08.05.2014  22:59  DIR            .eclipse",
        "type": "default"
      },
      {
        "message": "08.11.2015  20:03  DIR            .electron",
        "type": "default"
      },
      {
        "message": "08.11.2015  14:17           145 B .gitconfig",
        "type": "default"
      },
      {
        "message": "20.04.2014  13:32  DIR            .minion",
        "type": "default"
      },
      {
        "message": "23.06.2014  19:16  DIR            .ssh",
        "type": "default"
      },
      {
        "message": "07.06.2015  16:44  DIR            .thumbnails",
        "type": "default"
      },
      {
        "message": "26.04.2014  14:03  DIR            .VirtualBox",
        "type": "default"
      },
      {
        "message": "27.06.2015  21:48  DIR            .WebStorm10",
        "type": "default"
      },
      {
        "message": "04.06.2014  21:28  DIR            .WebStorm8",
        "type": "default"
      },
      {
        "message": "20.06.2015  15:08           135 B .yo-rc-global.json",
        "type": "default"
      },
      {
        "message": "06.08.2015  18:46  DIR            3D Objects",
        "type": "default"
      },
      {
        "message": "31.10.2015  15:24  DIR            Anwendungsdaten",
        "type": "default"
      },
      {
        "message": "05.08.2015  23:26  DIR            AppData",
        "type": "default"
      },
      {
        "message": "22.03.2014  12:31  DIR            Application Data",
        "type": "default"
      },
      {
        "message": "08.05.2014  22:58  DIR            Aptana Rubles",
        "type": "default"
      },
      {
        "message": "26.10.2015  20:19  DIR            Contacts",
        "type": "default"
      },
      {
        "message": "08.11.2015  22:50  DIR            Cookies",
        "type": "default"
      },
      {
        "message": "08.11.2015  23:00  DIR            Desktop",
        "type": "default"
      },
      {
        "message": "04.11.2015  08:34  DIR            Documents",
        "type": "default"
      },
      {
        "message": "08.11.2015  23:21  DIR            Downloads",
        "type": "default"
      },
      {
        "message": "10.07.2015  13:04  DIR            Druckumgebung",
        "type": "default"
      },
      {
        "message": "04.11.2015  08:34  DIR            Eigene Dateien",
        "type": "default"
      },
      {
        "message": "26.10.2015  20:19  DIR            Favorites",
        "type": "default"
      },
      {
        "message": "26.10.2015  20:19  DIR            Links",
        "type": "default"
      },
      {
        "message": "08.11.2015  13:02  DIR            Lokale Einstellungen",
        "type": "default"
      },
      {
        "message": "26.10.2015  20:19  DIR            Music",
        "type": "default"
      },
      {
        "message": "10.07.2015  13:04  DIR            Netzwerkumgebung",
        "type": "default"
      },
      {
        "message": "08.11.2015  03:31          3.7 MB NTUSER.DAT",
        "type": "default"
      },
      {
        "message": "05.08.2015  23:25        964.6 kB ntuser.dat.LOG1",
        "type": "default"
      },
      {
        "message": "05.08.2015  23:25        983.0 kB ntuser.dat.LOG2",
        "type": "default"
      },
      {
        "message": "17.10.2015  01:41         65.5 kB NTUSER.DAT{adb23442-271f-11e5-80dd-e41d2d719220}.TM.blf",
        "type": "default"
      },
      {
        "message": "17.10.2015  01:41        524.3 kB NTUSER.DAT{adb23442-271f-11e5-80dd-e41d2d719220}.TMContainer00000000000000000001.regtrans-ms",
        "type": "default"
      },
      {
        "message": "05.08.2015  23:25        524.3 kB NTUSER.DAT{adb23442-271f-11e5-80dd-e41d2d719220}.TMContainer00000000000000000002.regtrans-ms",
        "type": "default"
      },
      {
        "message": "06.08.2015  08:02            20 B ntuser.ini",
        "type": "default"
      },
      {
        "message": "06.08.2015  08:06  DIR            OneDrive",
        "type": "default"
      },
      {
        "message": "08.11.2015  23:16  DIR            Pictures",
        "type": "default"
      },
      {
        "message": "08.05.2014  22:42  DIR            projects",
        "type": "default"
      },
      {
        "message": "08.11.2015  23:21  DIR            Recent",
        "type": "default"
      },
      {
        "message": "26.10.2015  20:19  DIR            Saved Games",
        "type": "default"
      },
      {
        "message": "26.10.2015  20:19  DIR            Searches",
        "type": "default"
      },
      {
        "message": "16.10.2015  21:46  DIR            SendTo",
        "type": "default"
      },
      {
        "message": "07.08.2015  20:42  DIR            SkyDrive",
        "type": "default"
      },
      {
        "message": "31.03.2014  17:31  DIR            SkyDrive.old",
        "type": "default"
      },
      {
        "message": "26.10.2015  20:19  DIR            Startmenü",
        "type": "default"
      },
      {
        "message": "16.10.2015  21:47  DIR            Tracing",
        "type": "default"
      },
      {
        "message": "20.06.2015  00:20  DIR            typings",
        "type": "default"
      },
      {
        "message": "08.11.2015  13:06  DIR            Videos",
        "type": "default"
      },
      {
        "message": "26.04.2014  14:01  DIR            VirtualBox VMs",
        "type": "default"
      },
      {
        "message": "10.07.2015  13:04  DIR            Vorlagen",
        "type": "default"
      },
      {
        "message": "03.10.2015  09:09  DIR            WebstormProjects",
        "type": "default"
      },
      {
        "message": "C:\\Users\\Alexander> ls",
        "type": "command"
      },
      {
        "message": "08.11.2015  14:17  DIR            .",
        "type": "default"
      },
      {
        "message": "05.08.2015  23:27  DIR            ..",
        "type": "default"
      },
      {
        "message": "31.10.2015  15:28  DIR            .atom",
        "type": "default"
      },
      {
        "message": "27.06.2015  20:27  DIR            .config",
        "type": "default"
      },
      {
        "message": "08.05.2014  22:59  DIR            .eclipse",
        "type": "default"
      },
      {
        "message": "08.11.2015  20:03  DIR            .electron",
        "type": "default"
      },
      {
        "message": "08.11.2015  14:17           145 B .gitconfig",
        "type": "default"
      },
      {
        "message": "20.04.2014  13:32  DIR            .minion",
        "type": "default"
      },
      {
        "message": "23.06.2014  19:16  DIR            .ssh",
        "type": "default"
      },
      {
        "message": "07.06.2015  16:44  DIR            .thumbnails",
        "type": "default"
      },
      {
        "message": "26.04.2014  14:03  DIR            .VirtualBox",
        "type": "default"
      },
      {
        "message": "27.06.2015  21:48  DIR            .WebStorm10",
        "type": "default"
      },
      {
        "message": "04.06.2014  21:28  DIR            .WebStorm8",
        "type": "default"
      },
      {
        "message": "20.06.2015  15:08           135 B .yo-rc-global.json",
        "type": "default"
      },
      {
        "message": "06.08.2015  18:46  DIR            3D Objects",
        "type": "default"
      },
      {
        "message": "31.10.2015  15:24  DIR            Anwendungsdaten",
        "type": "default"
      },
      {
        "message": "05.08.2015  23:26  DIR            AppData",
        "type": "default"
      },
      {
        "message": "22.03.2014  12:31  DIR            Application Data",
        "type": "default"
      },
      {
        "message": "08.05.2014  22:58  DIR            Aptana Rubles",
        "type": "default"
      },
      {
        "message": "26.10.2015  20:19  DIR            Contacts",
        "type": "default"
      },
      {
        "message": "08.11.2015  22:50  DIR            Cookies",
        "type": "default"
      },
      {
        "message": "08.11.2015  23:00  DIR            Desktop",
        "type": "default"
      },
      {
        "message": "04.11.2015  08:34  DIR            Documents",
        "type": "default"
      },
      {
        "message": "08.11.2015  23:21  DIR            Downloads",
        "type": "default"
      },
      {
        "message": "10.07.2015  13:04  DIR            Druckumgebung",
        "type": "default"
      },
      {
        "message": "04.11.2015  08:34  DIR            Eigene Dateien",
        "type": "default"
      },
      {
        "message": "26.10.2015  20:19  DIR            Favorites",
        "type": "default"
      },
      {
        "message": "26.10.2015  20:19  DIR            Links",
        "type": "default"
      },
      {
        "message": "08.11.2015  13:02  DIR            Lokale Einstellungen",
        "type": "default"
      },
      {
        "message": "26.10.2015  20:19  DIR            Music",
        "type": "default"
      },
      {
        "message": "10.07.2015  13:04  DIR            Netzwerkumgebung",
        "type": "default"
      },
      {
        "message": "08.11.2015  03:31          3.7 MB NTUSER.DAT",
        "type": "default"
      },
      {
        "message": "05.08.2015  23:25        964.6 kB ntuser.dat.LOG1",
        "type": "default"
      },
      {
        "message": "05.08.2015  23:25        983.0 kB ntuser.dat.LOG2",
        "type": "default"
      },
      {
        "message": "17.10.2015  01:41         65.5 kB NTUSER.DAT{adb23442-271f-11e5-80dd-e41d2d719220}.TM.blf",
        "type": "default"
      },
      {
        "message": "17.10.2015  01:41        524.3 kB NTUSER.DAT{adb23442-271f-11e5-80dd-e41d2d719220}.TMContainer00000000000000000001.regtrans-ms",
        "type": "default"
      },
      {
        "message": "05.08.2015  23:25        524.3 kB NTUSER.DAT{adb23442-271f-11e5-80dd-e41d2d719220}.TMContainer00000000000000000002.regtrans-ms",
        "type": "default"
      },
      {
        "message": "06.08.2015  08:02            20 B ntuser.ini",
        "type": "default"
      },
      {
        "message": "06.08.2015  08:06  DIR            OneDrive",
        "type": "default"
      },
      {
        "message": "08.11.2015  23:16  DIR            Pictures",
        "type": "default"
      },
      {
        "message": "08.05.2014  22:42  DIR            projects",
        "type": "default"
      },
      {
        "message": "08.11.2015  23:21  DIR            Recent",
        "type": "default"
      },
      {
        "message": "26.10.2015  20:19  DIR            Saved Games",
        "type": "default"
      },
      {
        "message": "26.10.2015  20:19  DIR            Searches",
        "type": "default"
      },
      {
        "message": "16.10.2015  21:46  DIR            SendTo",
        "type": "default"
      },
      {
        "message": "07.08.2015  20:42  DIR            SkyDrive",
        "type": "default"
      },
      {
        "message": "31.03.2014  17:31  DIR            SkyDrive.old",
        "type": "default"
      },
      {
        "message": "26.10.2015  20:19  DIR            Startmenü",
        "type": "default"
      },
      {
        "message": "16.10.2015  21:47  DIR            Tracing",
        "type": "default"
      },
      {
        "message": "20.06.2015  00:20  DIR            typings",
        "type": "default"
      },
      {
        "message": "08.11.2015  13:06  DIR            Videos",
        "type": "default"
      },
      {
        "message": "26.04.2014  14:01  DIR            VirtualBox VMs",
        "type": "default"
      },
      {
        "message": "10.07.2015  13:04  DIR            Vorlagen",
        "type": "default"
      },
      {
        "message": "03.10.2015  09:09  DIR            WebstormProjects",
        "type": "default"
      }
    ],
    "history": [
      "ls"
    ],
    "cwd": "C:\\Users\\Alexander",
    "name": "test"
  }
]